{
  "project_info": {
    "project_number": "5511230237",
    "project_id": "project3-a4d8f",
    "storage_bucket": "project3-a4d8f.firebasestorage.app"
  },
  "client": [
    {
      "client_info": {
        "mobilesdk_app_id": "1:5511230237:android:b4d232686e6c19ba4427f4",
        "android_client_info": {
          "package_name": "com.example.project3"
        }
      },
      "oauth_client": [
        {
          "client_id": "5511230237-t2mbat0f8lhbail7nqmqf2lietf1me6u.apps.googleusercontent.com",
          "client_type": 1,
          "android_info": {
            "package_name": "com.example.project3",
            "certificate_hash": "e71a4e0482eea624cbd5624af70440be935fadae"
          }
        },
        {
          "client_id": "5511230237-sa2n654b5r5mri44q30p41lqnpb00pg4.apps.googleusercontent.com",
          "client_type": 3
        }
      ],
      "api_key": [
        {
          "current_key": "AIzaSyBCsevdsxZRAQO2Fy4Iw9qcFGRaBDwfUuQ"
        }
      ],
      "services": {
        "appinvite_service": {
          "other_platform_oauth_client": [
            {
              "client_id": "5511230237-sa2n654b5r5mri44q30p41lqnpb00pg4.apps.googleusercontent.com",
              "client_type": 3
            },
            {
              "client_id": "5511230237-1h1m6t8nifiu8cnaffh74bbi0q85gcqf.apps.googleusercontent.com",
              "client_type": 2,
              "ios_info": {
                "bundle_id": "com.example.project3"
              }
            }
          ]
        }
      }
    }
  ],
  "configuration_version": "1"
}